{
  "articles": [
    {
      "id": 3,
      "author": "Perceval",
      "chapter": "Livre IV",
      "episode": "Les Chaperons",
      "content": "En plus, je connais une technique pour tuer trois hommes en un coup rien qu’avec des feuilles mortes ! Alors là, vous êtes deux, vous avez bien de la chance.",
      "date": "",
      "image": "img/livre-4-les-chaperons.jpg"
    },
    {
      "id": 4,
      "author": "Karadoc",
      "chapter": "Livre II",
      "episode": "Sept cent quarante-quatre",
      "content": "Par exemple, vous prenez aujourd’hui. Vous comptez sept jours. Ça vous emmène dans une semaine. Et bien on sera exactement le même jour qu’aujourd’hui… À une vache près, hein… C’est pas une science exacte.",
      "date": "",
      "image": "img/livre-2-sept-cent-quarante-quatre.jpg"
    },
    {
      "author": "Kadoc",
      "chapter": "Livre II",
      "episode": "O'Brother",
      "content": "J'ai le droit d'être 4 jours pas chez moi, et après chez moi. Mais y a du voyage qui se prépare, et pour soigner les bêtes, y a pas que ma tante, y a moi aussi.",
      "date": "2017-03-17T11:17:17.863Z",
      "image": "",
      "id": 5
    },
    {
      "author": "Kadoc",
      "chapter": "Livre II",
      "episode": "Le Jeu du caillou",
      "content": "Les pattes de canaaaaaaaaaaaaaaaaaaaaaaaaaaaaard !",
      "date": "2017-03-17T11:21:11.836Z",
      "image": "",
      "id": 6
    },
    {
      "author": "Kadoc",
      "chapter": "Livre II",
      "episode": "Le Jeu du caillou",
      "content": "Mordu, mordu, mooooordu! Mordu mordu mordu mordu mordu mordu mordu mordu mordu mooooooooooordu !!!!",
      "date": "2017-03-17T11:22:25.775Z",
      "image": "",
      "id": 7
    },
    {
      "author": "Le Jeu du caillou",
      "chapter": "Livre II",
      "episode": "Le Jeu du caillou",
      "content": "Karadoc il s'occupe, mais c'est pas ma Tatan ! !",
      "date": "2017-03-17T11:27:04.172Z",
      "image": "",
      "id": 8
    },
    {
      "author": "Le Jeu du caillou",
      "chapter": "Livre II",
      "episode": "Le Jeu du caillou",
      "content": "Karadoc il s'occupe, mais c'est pas ma Tatan ! !",
      "date": "2017-03-17T11:27:10.306Z",
      "image": "",
      "id": 9
    },
    {
      "author": "Le Jeu du caillou",
      "chapter": "Livre II",
      "episode": "Le Jeu du caillou",
      "content": "Karadoc il s'occupe, mais c'est pas ma Tatan ! !",
      "date": "2017-03-17T11:27:12.270Z",
      "image": "",
      "id": 10
    },
    {
      "author": "Le Jeu du caillou",
      "chapter": "Livre II",
      "episode": "Le Jeu du caillou",
      "content": "Karadoc il s'occupe, mais c'est pas ma Tatan ! !",
      "date": "2017-03-17T11:27:14.321Z",
      "image": "",
      "id": 11
    },
    {
      "author": "Kadoc",
      "chapter": "Livre II",
      "episode": "Le Jeu du caillou",
      "content": "Karadoc il s'occupe, mais c'est pas ma Tatan ! !",
      "date": "2017-03-17T11:27:38.603Z",
      "image": "",
      "id": 12
    },
    {
      "author": "Kadoc",
      "chapter": "Livre II",
      "episode": "Le Jeu du caillou",
      "content": "Karadoc il s'occupe, mais c'est pas ma Tatan ! !",
      "date": "2017-03-17T11:27:45.066Z",
      "image": "",
      "id": 13
    },
    {
      "author": "qsd",
      "chapter": "qsd",
      "episode": "qsd",
      "content": "qsd",
      "date": "2017-03-17T12:14:04.589Z",
      "image": "",
      "id": 14
    }
  ]
}